{
  "answerArea": {
    "calculator": false,
    "chi2Table": false,
    "periodicTable": false,
    "tTable": false,
    "zTable": false
  },
  "hints": [
    {
      "content": "Let's use the place value blocks to help us solve. ",
      "images": {},
      "replace": false,
      "widgets": {}
    },
    {
      "content": "The first set of blocks has $\\blueE{13}$ place value blocks. \n\n![](web+graphie://cdn.kastatic.org/ka-perseus-graphie/69581e01528113251253bd43185f1a3db8a18876)",
      "images": {
        "web+graphie://cdn.kastatic.org/ka-perseus-graphie/69581e01528113251253bd43185f1a3db8a18876": {
          "height": 140,
          "width": 54,
          "alt": "alt text placeholder!"
        }
      },
      "replace": false,
      "widgets": {}
    },
    {
      "content": "The second set of blocks has $\\maroonD{4}$ place value blocks. \n\n![](web+graphie://cdn.kastatic.org/ka-perseus-graphie/bf88e5b8b9070b742be0b09c38af6a8a2b92c1ad)",
      "images": {
        "web+graphie://cdn.kastatic.org/ka-perseus-graphie/bf88e5b8b9070b742be0b09c38af6a8a2b92c1ad": {
          "height": 140,
          "width": 28,
          "alt": "alt text placeholder!"
        }
      },
      "replace": false,
      "widgets": {}
    },
    {
      "content": "Let's take away $\\maroonD4$ place value blocks from the $\\blueE{13}$ blocks.\n\n![](web+graphie://cdn.kastatic.org/ka-perseus-graphie/1bbaff25ce434f83e5d062b0f4178f823485ca8d)\n",
      "images": {
        "web+graphie://cdn.kastatic.org/ka-perseus-graphie/1bbaff25ce434f83e5d062b0f4178f823485ca8d": {
          "height": 140,
          "width": 54,
          "alt": "alt text placeholder!"
        }
      },
      "replace": false,
      "widgets": {}
    },
    {
      "content": "There are $\\blueE9$ blocks left.\n\n![](web+graphie://cdn.kastatic.org/ka-perseus-graphie/301bb28cd36c577d484fbcc439dcdb0c1f6868d5)",
      "images": {
        "web+graphie://cdn.kastatic.org/ka-perseus-graphie/301bb28cd36c577d484fbcc439dcdb0c1f6868d5": {
          "height": 200,
          "width": 38,
          "alt": "alt text placeholder!"
        }
      },
      "replace": false,
      "widgets": {}
    },
    {
      "content": "${}\\Large\\blueE9=\\blueE{13} - \\maroonD4$",
      "images": {},
      "replace": false,
      "widgets": {}
    }
  ],
  "itemDataVersion": {
    "major": 2,
    "minor": 0
  },
  "question": {
    "content": "**Subtract.**  \n*Hint: Use the place value blocks to help solve $13 - 4$.*\n\n [[☃ numeric-input 1]] ${}\\Large=\\blueE{13} - \\maroonD4$\n\n![](web+graphie://cdn.kastatic.org/ka-perseus-graphie/552734b86e1832b3364cf20780222bb7ffcb6fe2)",
    "images": {
      "web+graphie://cdn.kastatic.org/ka-perseus-graphie/552734b86e1832b3364cf20780222bb7ffcb6fe2": {
        "height": 140,
        "width": 105,
        "alt": "alt text placeholder!"
      }
    },
    "widgets": {
      "numeric-input 1": {
        "alignment": "default",
        "graded": true,
        "options": {
          "answers": [
            {
              "maxError": null,
              "message": "",
              "simplify": "required",
              "status": "correct",
              "strict": false,
              "value": 9
            }
          ],
          "coefficient": false,
          "labelText": "",
          "multipleNumberInput": false,
          "rightAlign": false,
          "size": "normal",
          "static": false
        },
        "static": false,
        "type": "numeric-input",
        "version": {
          "major": 2,
          "minor": 0
        }
      }
    }
  }
}