{
  "answerArea": {
    "calculator": false,
    "chi2Table": false,
    "financialCalculatorMonthlyPayment": false,
    "financialCalculatorTimeToPayOff": false,
    "financialCalculatorTotalAmount": false,
    "periodicTable": false,
    "periodicTableWithKey": false,
    "tTable": false,
    "zTable": false
  },
  "hints": [
    {
      "content": "The distance around a closed figure is called its perimeter.",
      "images": {},
      "replace": false,
      "widgets": {}
    },
    {
      "content": "\n\n[[☃ image 1]]\n\n \n\nThe sum of all the known lengths is:\n\n$\\blueD{14} + \\greenD{10} = \\maroonD{{24}\\,\\text{cm}}$.",
      "images": {},
      "replace": false,
      "widgets": {
        "image 1": {
          "alignment": "block",
          "graded": true,
          "options": {
            "alt": "A triangle with sides labeled as 14 centimeters, 10 centimeters, and question mark centimeters. !",
            "backgroundImage": {
              "height": 267,
              "url": "web+graphie://cdn.kastatic.org/ka-perseus-graphie/a477a4732a29c8d239e2ce0327db79905b669139",
              "width": 400
            },
            "box": [
              400,
              267
            ],
            "caption": "",
            "labels": [],
            "range": [
              [
                0,
                10
              ],
              [
                0,
                10
              ]
            ],
            "static": false,
            "title": ""
          },
          "static": false,
          "type": "image",
          "version": {
            "major": 2,
            "minor": 0
          }
        }
      }
    },
    {
      "content": "The total perimeter is $41\\,\\text{cm}$.  \n\nSubtract the known lengths from  $41\\,\\text{cm}$ to find the missing length.  \n\n$41 - \\maroonD{24} = \\purpleC{17\\,\\text{ cm}}$",
      "images": {},
      "replace": false,
      "widgets": {}
    },
    {
      "content": "The missing side length is  $\\purpleC {17\\,\\text{cm}}$.",
      "images": {},
      "replace": false,
      "widgets": {}
    }
  ],
  "question": {
    "content": "The perimeter of the figure is $41\\text{ cm}$.   \n\n[[☃ image 1]]\n\n **What is the length of the missing side?**  \n\n[[☃ numeric-input 1]] $\\text{cm}$",
    "images": {},
    "widgets": {
      "image 1": {
        "alignment": "block",
        "graded": true,
        "options": {
          "alt": "A triangle with sides labeled as 14 centimeters, 10 centimeters, and question mark centimeters. !",
          "backgroundImage": {
            "height": 266,
            "url": "https://cdn.kastatic.org/ka-perseus-graphie/b6896f312062f5765029c3841e118985a064e698.png",
            "width": 400
          },
          "box": [
            400,
            266
          ],
          "caption": "",
          "labels": [],
          "range": [
            [
              0,
              10
            ],
            [
              0,
              10
            ]
          ],
          "static": false,
          "title": ""
        },
        "static": false,
        "type": "image",
        "version": {
          "major": 2,
          "minor": 0
        }
      },
      "numeric-input 1": {
        "alignment": "default",
        "graded": true,
        "options": {
          "answers": [
            {
              "maxError": null,
              "message": "",
              "simplify": "required",
              "status": "correct",
              "strict": false,
              "value": 17
            }
          ],
          "coefficient": false,
          "labelText": "length of the missing side",
          "rightAlign": false,
          "size": "normal",
          "static": false
        },
        "static": false,
        "type": "numeric-input",
        "version": {
          "major": 2,
          "minor": 0
        }
      }
    }
  }
}