{
  "answerArea": {
    "calculator": false,
    "chi2Table": false,
    "periodicTable": false,
    "tTable": false,
    "zTable": false
  },
  "hints": [
    {
      "content": "![](web+graphie://cdn.kastatic.org/ka-perseus-graphie/ef3010e99bd8f2c2124bb094514860abbdad0c46)",
      "images": {
        "web+graphie://cdn.kastatic.org/ka-perseus-graphie/ef3010e99bd8f2c2124bb094514860abbdad0c46": {
          "height": 160,
          "width": 240,
          "alt": "alt text placeholder!"
        }
      },
      "replace": true,
      "widgets": {}
    },
    {
      "content": "![](web+graphie://cdn.kastatic.org/ka-perseus-graphie/f99dfb33d495bf411d605e8c97bca367341bf1a1)\n\n",
      "images": {
        "web+graphie://cdn.kastatic.org/ka-perseus-graphie/f99dfb33d495bf411d605e8c97bca367341bf1a1": {
          "height": 160,
          "width": 240,
          "alt": "alt text placeholder!"
        }
      },
      "replace": true,
      "widgets": {}
    },
    {
      "content": "![](web+graphie://cdn.kastatic.org/ka-perseus-graphie/0c7fa8ca358769fb119f3b5d11cb91937788c864)",
      "images": {
        "web+graphie://cdn.kastatic.org/ka-perseus-graphie/0c7fa8ca358769fb119f3b5d11cb91937788c864": {
          "height": 160,
          "width": 240,
          "alt": "alt text placeholder!"
        }
      },
      "replace": true,
      "widgets": {}
    },
    {
      "content": "![](web+graphie://cdn.kastatic.org/ka-perseus-graphie/7d522e1af7be7332db17635029cdf1ce1086c29e)",
      "images": {
        "web+graphie://cdn.kastatic.org/ka-perseus-graphie/7d522e1af7be7332db17635029cdf1ce1086c29e": {
          "height": 160,
          "width": 240,
          "alt": "alt text placeholder!"
        }
      },
      "replace": true,
      "widgets": {}
    },
    {
      "content": "![](web+graphie://cdn.kastatic.org/ka-perseus-graphie/4b08d20443983c19562af30d034816a69ebd4586)",
      "images": {
        "web+graphie://cdn.kastatic.org/ka-perseus-graphie/4b08d20443983c19562af30d034816a69ebd4586": {
          "height": 160,
          "width": 240,
          "alt": "alt text placeholder!"
        }
      },
      "replace": true,
      "widgets": {}
    },
    {
      "content": "![](web+graphie://cdn.kastatic.org/ka-perseus-graphie/be90a302b4ad9acecf336d349ad142ec94ea37a4)",
      "images": {
        "web+graphie://cdn.kastatic.org/ka-perseus-graphie/be90a302b4ad9acecf336d349ad142ec94ea37a4": {
          "height": 160,
          "width": 240,
          "alt": "alt text placeholder!"
        }
      },
      "replace": true,
      "widgets": {}
    },
    {
      "content": "$\\large\\begin{align} 783{,}216& \\\\\n\\underline{-771{,}245}& \\\\\n11{,}971\n\\end{align}$",
      "images": {},
      "replace": false,
      "widgets": {}
    }
  ],
  "itemDataVersion": {
    "major": 2,
    "minor": 0
  },
  "question": {
    "content": "**Subtract.**\n\n$\\large\\begin{align} 783{,}216& \\\\\n\\underline{-771{,}245}& \\\\\n\\end{align}$\n\n\n[[☃ numeric-input 1]]",
    "images": {},
    "widgets": {
      "numeric-input 1": {
        "alignment": "default",
        "graded": true,
        "options": {
          "answers": [
            {
              "maxError": 0,
              "message": "",
              "simplify": "optional",
              "status": "correct",
              "strict": false,
              "value": 11971
            }
          ],
          "coefficient": false,
          "labelText": "",
          "multipleNumberInput": false,
          "rightAlign": true,
          "size": "normal",
          "static": false
        },
        "static": false,
        "type": "numeric-input",
        "version": {
          "major": 2,
          "minor": 0
        }
      }
    }
  }
}