{
  "answerArea": {
    "calculator": false,
    "chi2Table": false,
    "periodicTable": false,
    "tTable": false,
    "zTable": false
  },
  "hints": [
    {
      "content": "An $\\blueE{\\text{even}}$ number is a number that can be split into $2$ equal groups.\n\nWe find $\\blueE{\\text{even}}$ numbers by making sure every object in the group has a pair.\n\n![](web+graphie://cdn.kastatic.org/ka-perseus-graphie/9d50cd961bb1ee962eb60cc708a5e737e9d4486c)\n\nExamples of $\\blueE{\\text{even}}$ numbers are $\\blueE2, \\blueE4,\\blueE6, \\blueE8, \\blueE{10},  . .  .$",
      "images": {
        "web+graphie://cdn.kastatic.org/ka-perseus-graphie/9d50cd961bb1ee962eb60cc708a5e737e9d4486c": {
          "height": 87,
          "width": 120,
          "alt": "alt text placeholder!"
        }
      },
      "replace": false,
      "widgets": {}
    },
    {
      "content": "An $\\maroonD{\\text{odd}}$ number **cannot** be split into $2$ equal groups. \n\nWe find $\\maroonD{\\text{odd}}$ numbers by trying to pair objects and finding there is **not** always a pair.\n\n![](web+graphie://cdn.kastatic.org/ka-perseus-graphie/10c3af09ebfcd0c6d05b4edd219f33894cc4d8b9)\n\nExamples of $\\maroonD{\\text{odd}}$ numbers are $\\maroonD1, \\maroonD3, \\maroonD5, \\maroonD7, \\maroonD9, . . . $",
      "images": {
        "web+graphie://cdn.kastatic.org/ka-perseus-graphie/10c3af09ebfcd0c6d05b4edd219f33894cc4d8b9": {
          "height": 120,
          "width": 87,
          "alt": "alt text placeholder!"
        }
      },
      "replace": false,
      "widgets": {}
    },
    {
      "content": "In this image, there are $\\maroonD7$ pigs.\n\n![](web+graphie://cdn.kastatic.org/ka-perseus-graphie/b4fa182e48b6c60c3d1998258bc94d03fbfa05f0)\n\nEach pig does **not** have a pair, so there are an odd number of pigs.",
      "images": {
        "web+graphie://cdn.kastatic.org/ka-perseus-graphie/b4fa182e48b6c60c3d1998258bc94d03fbfa05f0": {
          "height": 99,
          "width": 175,
          "alt": "alt text placeholder!"
        }
      },
      "replace": false,
      "widgets": {}
    },
    {
      "content": "In this image, there are $\\blueE6$ eggs.\n\n![](web+graphie://cdn.kastatic.org/ka-perseus-graphie/4550571e0d12949615f1617fbd913437f9db7658)\n\nEach egg has a pair, so there are an even number of eggs.",
      "images": {
        "web+graphie://cdn.kastatic.org/ka-perseus-graphie/4550571e0d12949615f1617fbd913437f9db7658": {
          "height": 133,
          "width": 175,
          "alt": "alt text placeholder!"
        }
      },
      "replace": false,
      "widgets": {}
    },
    {
      "content": "In this image, there are $\\maroonD3$ sharks.\n\n![](web+graphie://cdn.kastatic.org/ka-perseus-graphie/7d7f96c886eed31d1e24590b1a8f17eafa033759)\n\nEach shark does **not** have a pair, so there are an odd number of sharks.",
      "images": {
        "web+graphie://cdn.kastatic.org/ka-perseus-graphie/7d7f96c886eed31d1e24590b1a8f17eafa033759": {
          "height": 79,
          "width": 175,
          "alt": "alt text placeholder!"
        }
      },
      "replace": false,
      "widgets": {}
    },
    {
      "content": "Here is the completed table:\n\nImage | Even/Odd\n- | - | -\n![](web+graphie://cdn.kastatic.org/ka-perseus-graphie/89e0d9b412aeedb876f0f6885c904a5054bdde5d) | **Odd**\n![](web+graphie://cdn.kastatic.org/ka-perseus-graphie/cf958c80fbfec114f3aeabc9a2c54d2db9803623) | **Even**\n![](web+graphie://cdn.kastatic.org/ka-perseus-graphie/591e2da531e474dd1dcc419d7bf818a27fd90f99)  | **Odd**",
      "images": {
        "web+graphie://cdn.kastatic.org/ka-perseus-graphie/591e2da531e474dd1dcc419d7bf818a27fd90f99": {
          "height": 79,
          "width": 175,
          "alt": "alt text placeholder!"
        },
        "web+graphie://cdn.kastatic.org/ka-perseus-graphie/89e0d9b412aeedb876f0f6885c904a5054bdde5d": {
          "height": 127,
          "width": 225,
          "alt": "alt text placeholder!"
        },
        "web+graphie://cdn.kastatic.org/ka-perseus-graphie/cf958c80fbfec114f3aeabc9a2c54d2db9803623": {
          "height": 133,
          "width": 175,
          "alt": "alt text placeholder!"
        }
      },
      "replace": false,
      "widgets": {}
    }
  ],
  "itemDataVersion": {
    "major": 2,
    "minor": 0
  },
  "question": {
    "content": "**Determine whether the number of objects is even or odd.**\n\nImage | Even/Odd\n- | - | -\n![](web+graphie://cdn.kastatic.org/ka-perseus-graphie/89e0d9b412aeedb876f0f6885c904a5054bdde5d) | [[☃ dropdown 1]]\n![](web+graphie://cdn.kastatic.org/ka-perseus-graphie/cf958c80fbfec114f3aeabc9a2c54d2db9803623) | [[☃ dropdown 2]]\n![](web+graphie://cdn.kastatic.org/ka-perseus-graphie/591e2da531e474dd1dcc419d7bf818a27fd90f99)  | [[☃ dropdown 3]]",
    "images": {
      "web+graphie://cdn.kastatic.org/ka-perseus-graphie/591e2da531e474dd1dcc419d7bf818a27fd90f99": {
        "height": 79,
        "width": 175,
        "alt": "alt text placeholder!"
      },
      "web+graphie://cdn.kastatic.org/ka-perseus-graphie/89e0d9b412aeedb876f0f6885c904a5054bdde5d": {
        "height": 127,
        "width": 225,
        "alt": "alt text placeholder!"
      },
      "web+graphie://cdn.kastatic.org/ka-perseus-graphie/cf958c80fbfec114f3aeabc9a2c54d2db9803623": {
        "height": 133,
        "width": 175,
        "alt": "alt text placeholder!"
      }
    },
    "widgets": {
      "dropdown 1": {
        "alignment": "default",
        "graded": true,
        "options": {
          "choices": [
            {
              "content": "Even",
              "correct": false
            },
            {
              "content": "Odd",
              "correct": true
            }
          ],
          "placeholder": "",
          "static": false
        },
        "static": false,
        "type": "dropdown",
        "version": {
          "major": 2,
          "minor": 0
        }
      },
      "dropdown 2": {
        "alignment": "default",
        "graded": true,
        "options": {
          "choices": [
            {
              "content": "Even",
              "correct": true
            },
            {
              "content": "Odd",
              "correct": false
            }
          ],
          "placeholder": "",
          "static": false
        },
        "static": false,
        "type": "dropdown",
        "version": {
          "major": 2,
          "minor": 0
        }
      },
      "dropdown 3": {
        "alignment": "default",
        "graded": true,
        "options": {
          "choices": [
            {
              "content": "Even",
              "correct": false
            },
            {
              "content": "Odd",
              "correct": true
            }
          ],
          "placeholder": "",
          "static": false
        },
        "static": false,
        "type": "dropdown",
        "version": {
          "major": 2,
          "minor": 0
        }
      }
    }
  }
}