{
  "answerArea": {
    "calculator": false,
    "chi2Table": false,
    "periodicTable": false,
    "tTable": false,
    "zTable": false
  },
  "hints": [
    {
      "content": "If we divide $\\purpleC{45}$ into $\\greenD9$ equal groups, how big is each group?\n\n[[☃ image 1]]\n\n\n",
      "images": {},
      "replace": false,
      "widgets": {
        "image 1": {
          "alignment": "block",
          "graded": true,
          "options": {
            "alt": "A tape diagram with 2 tapes of equal lengths, a first tape labeled 45 and a second tape with 9 equal parts each labeled with the letter y. A curved bracket below the second tape is labeled 9 equal groups. !",
            "backgroundImage": {
              "height": 128,
              "url": "web+graphie://cdn.kastatic.org/ka-perseus-graphie/ad1f3568f3cd09a13545c0b1af0bcd93bfd8582d",
              "width": 320
            },
            "box": [
              320,
              128
            ],
            "caption": "",
            "labels": [],
            "range": [
              [
                0,
                10
              ],
              [
                0,
                10
              ]
            ],
            "static": false,
            "title": ""
          },
          "static": false,
          "type": "image",
          "version": {
            "major": 2,
            "minor": 0
          }
        }
      }
    },
    {
      "content": "$\\greenD{9}\\times \\maroonD{y} = \\purpleC{45}$",
      "images": {},
      "replace": false,
      "widgets": {}
    }
  ],
  "itemDataVersion": {
    "major": 2,
    "minor": 0
  },
  "question": {
    "content": "Enzo saw $45$ squirrels at the park.  This was $9$ times as many squirrels as he saw in his yard.\n\n**Which equation will help us find how many squirrels $(y)$ Enzo saw in his yard?**  \n\n[[☃ radio 1]]\n\n",
    "images": {},
    "widgets": {
      "radio 1": {
        "alignment": "default",
        "graded": true,
        "options": {
          "choices": [
            {
              "content": "$9\\times45 =  y$",
              "correct": false,
              "id": "5bc11d4a-221a-4398-9450-424952498ada"
            },
            {
              "content": "$9 \\times y = 45$",
              "correct": true,
              "id": "d7d71ae1-2abc-4cab-83ff-b5b5cfb0050f"
            },
            {
              "content": "$y\\times45=9$",
              "isNoneOfTheAbove": false,
              "id": "7fd7636a-3616-4d01-b209-ae3878dd3393"
            }
          ],
          "countChoices": false,
          "deselectEnabled": false,
          "displayCount": null,
          "hasNoneOfTheAbove": false,
          "multipleSelect": false,
          "randomize": true
        },
        "static": false,
        "type": "radio",
        "version": {
          "major": 2,
          "minor": 0
        }
      }
    }
  }
}