{
  "answerArea": {
    "calculator": false,
    "chi2Table": false,
    "periodicTable": false,
    "tTable": false,
    "zTable": false
  },
  "hints": [
    {
      "content": "Partial products help us multiply larger numbers.\n\nWe can break the first factor apart by place value and multiply the parts *in any order* by the parts of the second factor. Then we add those products to get the final product.\n\n[[☃ explanation 1]]\n\nLet's take a look at how Leah broke apart the numbers to multiply.",
      "images": {},
      "replace": false,
      "widgets": {
        "explanation 1": {
          "alignment": "default",
          "graded": true,
          "options": {
            "explanation": "$54\\times 26$\n\nWe can break apart $54$ into $50 + 4$ and break apart $26$ into $20+6$.\n\n[[☃ image 1]]\n\nWe can start by multiplying $50\\times 20$ , $50\\times 6$, $4\\times 20$ or $4\\times6 $. The order does not matter since we will be adding all the products together.\n\n$\\begin{array}{rr}\n&\\begin{align}\n54&\\\\\n\\underline{{} \\times 26}\\end{align}\\\\\n\\text{any order}&\\left\\{\\begin{align}\n1{,}000\\\\\n300\\\\\n80\\\\\n\\underline{{}+24}\\end{align}\\right.\\\\\n&\\begin{align}\n1{,}404\n\\end{align}\n\\end{array}$",
            "hidePrompt": "Got it, thanks!",
            "showPrompt": "Can you show me an example please?",
            "static": false,
            "widgets": {
              "image 1": {
                "alignment": "block",
                "graded": true,
                "options": {
                  "alt": "A rectangular array split in 4 parts. The top left part has a height of 6 and a base of 50. The top right part has a height of 6 and a base of 4. The bottom left part has a height of 20 and a base of 50. The bottom right part has a height of 20 and a base of 4. The left side of the array is labeled 6 plus 20. The bottom of the array is labeled 50 plus 4.",
                  "backgroundImage": {
                    "height": 178,
                    "url": "web+graphie://cdn.kastatic.org/ka-perseus-graphie/8896924564478ceda9e4a46cbb6ed7afe8f30d35",
                    "width": 320
                  },
                  "box": [
                    320,
                    178
                  ],
                  "caption": "",
                  "labels": [],
                  "range": [
                    [
                      0,
                      10
                    ],
                    [
                      0,
                      10
                    ]
                  ],
                  "static": false,
                  "title": ""
                },
                "static": false,
                "type": "image",
                "version": {
                  "major": 0,
                  "minor": 0
                }
              }
            }
          },
          "static": false,
          "type": "explanation",
          "version": {
            "major": 2,
            "minor": 0
          }
        }
      }
    },
    {
      "content": "###Step $1$\n\n$\\begin{align}\n\\goldE{1}5&\\\\\n\\underline{{} \\times \\goldE{5}8}&\\\\\n\\goldE{500}&\\quad \\goldE{50} \\times \\goldE{10}\n\\end{align}$\n\nThere are $5$ tens in $58$, and there is $1$ ten in $15$.  Also,\n$\\goldE{50}\\times\\goldE{10}=\\goldE{500}$, so Leah did not make a mistake in step $1$.",
      "images": {},
      "replace": false,
      "widgets": {}
    },
    {
      "content": "###Step $2$\n\n$\\begin{align}\n1\\maroonE{5}&\\\\\n\\underline{{} \\times \\maroonE{5}8}&\\\\\n500&\\quad 50 \\times 10\\\\\n\\maroonE{250}&\\quad \\maroonE{50} \\times \\maroonE{5}\n\\end{align}$\n\nThere are $5$ tens in $58$, and there are $5$ ones in $15$.  Also,\n$\\maroonE{50}\\times\\maroonE{5}=\\maroonE{250}$, so Leah did not make a mistake in step $2$.",
      "images": {},
      "replace": false,
      "widgets": {}
    },
    {
      "content": "###Step $3$\n\n$\\begin{align}\n\\tealE{1}5&\\\\\n\\underline{{} \\times 5\\tealE{8}}&\\\\\n500&\\quad 50 \\times 10 \\\\\n250&\\quad 50 \\times 5 \\\\\n\\tealE{80}&\\quad \\tealE{8} \\times \\tealE{10}\n\\end{align}$\n\nLeah said that $\\tealE{8}\\times\\tealE{10}$ equals $800$, so Leah made a mistake in step $3$. ",
      "images": {},
      "replace": false,
      "widgets": {}
    },
    {
      "content": "Leah made a mistake in step $3$.",
      "images": {},
      "replace": false,
      "widgets": {}
    }
  ],
  "itemDataVersion": {
    "major": 2,
    "minor": 0
  },
  "question": {
    "content": "Leah tried to evaluate $15\\times58$ using partial products, but she made a mistake.  Her work is below.\n\n$\\begin{array}{llrr}\n&&15 \\\\\n&&\\underline{{}\\times58} \\\\\n&\\goldE{\\text{Step 1}}&\\goldE{500}& \\goldE{50\\times 10}\\\\\n&\\maroonE{\\text{Step 2}}&\\maroonE{250}& \\maroonE{50\\times 5}\\\\\n&\\tealE{\\text{Step 3}}&\\tealE{800}& \\tealE{8\\times 10}\\\\\n&\\blueE{\\text{Step 4}}&\\underline{{}+\\blueE{40}}& \\blueE{8\\times5}\\\\\n&\\purpleE{\\text{Step 5}}&\\purpleE{1{,}590}&\n \\end{array}$\n\n**Find Leah's mistake.**\n\n[[☃ radio 1]]",
    "images": {},
    "widgets": {
      "radio 1": {
        "alignment": "default",
        "graded": true,
        "options": {
          "choices": [
            {
              "clue": "There are $5$ tens in $58$, and there is $1$ ten in $15$.  Also,\n$\\goldE{50}\\times\\goldE{10}=\\goldE{500}$, so Leah did not make a mistake in step $1$.",
              "content": "$\\goldE{\\text{Step }1}$",
              "correct": false,
              "id": "eda9b7ae-58b5-412f-8416-16cbf3af5ce8"
            },
            {
              "clue": "There are $5$ tens in $58$, and there are $5$ ones in $15$.  Also,\n$\\maroonE{50}\\times\\maroonE{5}=\\maroonE{250}$, so Leah did not make a mistake in step $2$.",
              "content": "$\\maroonE{\\text{Step }2}$",
              "correct": false,
              "id": "175e87d9-5860-49e1-abc5-f543b041827d"
            },
            {
              "clue": "$\\tealE{8}\\times\\tealE{10}=80$, not $800$. So Leah made a mistake in step $3$.",
              "content": "$\\tealE{\\text{Step }3}$",
              "correct": true,
              "isNoneOfTheAbove": false,
              "id": "9f112d69-3cc5-496a-89e9-0e7cdece16aa"
            },
            {
              "clue": "There are $8$ ones in $58$, and there are $5$ ones in $15$.  Also,\n$\\blueE{8}\\times\\blueE{5}=\\blueE{40}$, so Leah did not make a mistake in step $4$.",
              "content": "$\\blueE{\\text{Step }4}$",
              "correct": false,
              "isNoneOfTheAbove": false,
              "id": "32336da3-bd9c-488a-bc89-6f31b9c042c4"
            },
            {
              "clue": "Leah correctly added her four partial products.",
              "content": "$\\purpleE{\\text{Step }5}$",
              "correct": false,
              "isNoneOfTheAbove": false,
              "id": "a0952692-34e2-4384-936b-df73faa06265"
            }
          ],
          "countChoices": false,
          "deselectEnabled": false,
          "displayCount": null,
          "hasNoneOfTheAbove": false,
          "multipleSelect": false,
          "randomize": false
        },
        "static": false,
        "type": "radio",
        "version": {
          "major": 2,
          "minor": 0
        }
      }
    }
  }
}