{
  "answerArea": {
    "calculator": false,
    "chi2Table": false,
    "periodicTable": false,
    "tTable": false,
    "zTable": false
  },
  "hints": [
    {
      "content": "We can relate multiplication and division:\n\n\n$\\begin{align}\n\\blueD{\\text{Number of groups}}&\\times\\purpleC{\\text{ size of the group}} = \\greenD{\\text{ total}}\\\\\\\\\n\\purpleC{\\text{Size of the group}}&\\times\\blueD{\\text{ number of groups}} = \\greenD{\\text{ total}}\\\\\\\\\n \\greenD{\\text{Total}}&\\div\\blueD{\\text{ number of groups}} =\\purpleC{\\text{ size of the groups}}\\\\\\\\\n \\greenD{\\text{Total}}&\\div\\purpleC{\\text{ size of the groups}}=\\blueD{\\text{ number of groups}} \n\\end{align}$",
      "images": {},
      "replace": false,
      "widgets": {}
    },
    {
      "content": "If we have $\\blueD8$ groups of $\\purpleC5$, how many total do we have? ",
      "images": {},
      "replace": false,
      "widgets": {}
    },
    {
      "content": "There are $\\greenD{40}$ total.\n\n$\\underbrace{\\purpleC{5} + \\purpleC{5} + \\purpleC{5} + \\purpleC{5}+\\purpleC{5} + \\purpleC{5} + \\purpleC{5}+\\purpleC{5}}_{\\blueD{8}\\purpleC{\\text{ fives}}} = \\greenD{40}$",
      "images": {},
      "replace": false,
      "widgets": {}
    },
    {
      "content": "$\\fbox{\\greenD{40}}\\div\\purpleC{5} = \\blueD{8}$ $~~$ because  $~~$ $\\blueD8\\times\\purpleC5=\\fbox{\\greenD{40}}$.",
      "images": {},
      "replace": false,
      "widgets": {}
    }
  ],
  "itemDataVersion": {
    "major": 2,
    "minor": 0
  },
  "question": {
    "content": "**Fill in the blanks.**\n\n[[☃ input-number 3]] $~\\div$ $5=8$ $~~$ because  $~~$ $8\\times5=$ [[☃ input-number 4]].\n\n",
    "images": {},
    "widgets": {
      "input-number 3": {
        "alignment": "default",
        "graded": true,
        "options": {
          "answerType": "number",
          "inexact": false,
          "maxError": 0.1,
          "simplify": "required",
          "size": "small",
          "value": 40
        },
        "static": false,
        "type": "input-number",
        "version": {
          "major": 2,
          "minor": 0
        }
      },
      "input-number 4": {
        "alignment": "default",
        "graded": true,
        "options": {
          "answerType": "number",
          "inexact": false,
          "maxError": 0.1,
          "simplify": "required",
          "size": "small",
          "value": 40
        },
        "static": false,
        "type": "input-number",
        "version": {
          "major": 2,
          "minor": 0
        }
      }
    }
  }
}