{
  "answerArea": {
    "calculator": false,
    "chi2Table": false,
    "periodicTable": false,
    "tTable": false,
    "zTable": false
  },
  "hints": [
    {
      "content": "Let's look whether each multiple of $6$ is odd or even.",
      "images": {},
      "replace": false,
      "widgets": {}
    },
    {
      "content": "Multiple | Is even?\n-: | :-:\n$6$ | yes\n$12$ | yes\n$18$ | yes\n$24$ | yes\n$30$ | yes\n$36$ | yes\n$42$ | yes\n$48$ | yes\n$54$ | yes\n$60$ | yes\n$66$ | yes\n$72$ | yes\n$78$ | yes\n$84$ | yes\n$90$ | yes\n$96$ | yes\n\nFor all the multiples in the table, the statement is true.",
      "images": {},
      "replace": false,
      "widgets": {}
    },
    {
      "content": "Does this work for any number?\n\nAny whole number times $2$ is even.\n\n$\\begin{align}\nn \\times 6 &=n \\times (3 \\times 2) \\\\\\\\\n&=n \\times 3 \\times 2 \\\\\\\\\n&=(n \\times 3) \\times 2\n\\end{align}$\n\nYes, the statement is **always** true.",
      "images": {},
      "replace": false,
      "widgets": {}
    },
    {
      "content": "When we multiply by $6$, we *always* get an even number.",
      "images": {},
      "replace": false,
      "widgets": {}
    }
  ],
  "itemDataVersion": {
    "major": 2,
    "minor": 0
  },
  "question": {
    "content": "The hundred chart has the multiples of $6$ shaded.\n\n**When we multiply by $6$, we [[☃ dropdown 1]] get an even number.**  \n\n![hundred chart with multiples of 6 shaded: 6, 12, 18, 24, 30, 36, 42, 48, 54, 60, 66, 72, 78, 84, 90, 96](web+graphie://cdn.kastatic.org/ka-perseus-graphie/8e6d3987e7ea646d4155e988f715cd5a8f9b7fc7)",
    "images": {
      "web+graphie://cdn.kastatic.org/ka-perseus-graphie/8e6d3987e7ea646d4155e988f715cd5a8f9b7fc7": {
        "height": 317,
        "width": 320,
        "alt": "alt text placeholder!"
      }
    },
    "widgets": {
      "dropdown 1": {
        "alignment": "default",
        "graded": true,
        "options": {
          "choices": [
            {
              "content": "sometimes",
              "correct": false
            },
            {
              "content": "always",
              "correct": true
            },
            {
              "content": "never",
              "correct": false
            }
          ],
          "placeholder": "sometimes/always/never",
          "static": false
        },
        "static": false,
        "type": "dropdown",
        "version": {
          "major": 2,
          "minor": 0
        }
      }
    }
  }
}