{
  "answerArea": {
    "calculator": false,
    "options": {
      "content": "",
      "images": {},
      "widgets": {}
    },
    "periodicTable": false,
    "type": "multiple"
  },
  "hints": [
    {
      "content": "$21\\blueD9{,}775$ can be represented as follows:\n\n$=200{,}000 +10{,}000+ \\blueD{9000}+700+70+5$",
      "images": {},
      "widgets": {}
    },
    {
      "content": "$ \\blueD{9000}=\\blueD{9\\text{ thousands}}$",
      "images": {},
      "widgets": {}
    },
    {
      "content": "$\\blueD9$ is in the thousands place.",
      "images": {},
      "widgets": {}
    }
  ],
  "itemDataVersion": {
    "major": 0,
    "minor": 1
  },
  "question": {
    "content": "**What is the place value of the $\\blueD9$ in $21\\blueD9{,}775$?**\n\n[[☃ radio 1]]\n\n",
    "images": {},
    "widgets": {
      "radio 1": {
        "alignment": "default",
        "graded": true,
        "options": {
          "choices": [
            {
              "content": "Hundreds",
              "correct": false,
              "isNoneOfTheAbove": false
            },
            {
              "content": "Thousands",
              "correct": true,
              "isNoneOfTheAbove": false
            },
            {
              "content": "Ten thousands",
              "correct": false,
              "isNoneOfTheAbove": false
            },
            {
              "content": "Hundred thousands",
              "correct": false,
              "isNoneOfTheAbove": false
            }
          ],
          "deselectEnabled": false,
          "displayCount": null,
          "hasNoneOfTheAbove": false,
          "multipleSelect": false,
          "onePerLine": true,
          "randomize": false
        },
        "type": "radio",
        "version": {
          "major": 1,
          "minor": 0
        }
      }
    }
  }
}